{"follow_request_sent": false, "profile_use_background_image": true, "id": 1648668355, "verified": true, "profile_text_color": "333333", "profile_image_url_https": "https://pbs.twimg.com/profile_images/453909148095090688/8Nlg9-fy_normal.jpeg", "profile_sidebar_fill_color": "DDEEF6", "is_translator": false, "geo_enabled": false, "entities": {"url": {"urls": [{"url": "http://t.co/5rrYPh82Kr", "indices": [0, 22], "expanded_url": "http://www.vfemmes.com", "display_url": "vfemmes.com"}]}, "description": {"urls": []}}, "followers_count": 460, "protected": false, "location": "Milwaukee, Wisconsin", "default_profile_image": false, "id_str": "1648668355", "status": {"contributors": null, "truncated": false, "text": "See you at Common Ground Fest July 9th! with 311, the Wailers, Flobots, OPM, Radical Something, and more! Lansing, MI\nhttp://t.co/J8nQ6OOj38", "in_reply_to_status_id": null, "id": 456454000997834752, "favorite_count": 17, "source": "web", "retweeted": false, "coordinates": null, "entities": {"symbols": [], "user_mentions": [], "hashtags": [], "urls": [{"url": "http://t.co/J8nQ6OOj38", "indices": [118, 140], "expanded_url": "http://www.commongroundfest.com/", "display_url": "commongroundfest.com"}]}, "in_reply_to_screen_name": null, "id_str": "456454000997834752", "retweet_count": 7, "in_reply_to_user_id": null, "favorited": false, "geo": null, "in_reply_to_user_id_str": null, "possibly_sensitive": false, "lang": "en", "created_at": "Wed Apr 16 15:28:09 +0000 2014", "in_reply_to_status_id_str": null, "place": null}, "lang": "en", "utc_offset": -10800, "statuses_count": 10, "description": "Years of Disorganized Music", "friends_count": 104, "profile_link_color": "0C5AF5", "profile_image_url": "http://pbs.twimg.com/profile_images/453909148095090688/8Nlg9-fy_normal.jpeg", "notifications": false, "profile_background_image_url_https": "https://pbs.twimg.com/profile_background_images/450685689177198592/MExFOzkp.jpeg", "profile_background_color": "050505", "profile_banner_url": "https://pbs.twimg.com/profile_banners/1648668355/1397673275", "profile_background_image_url": "http://pbs.twimg.com/profile_background_images/450685689177198592/MExFOzkp.jpeg", "name": "Violent Femmes", "is_translation_enabled": false, "profile_background_tile": false, "favourites_count": 119, "screen_name": "violentfemmes", "url": "http://t.co/5rrYPh82Kr", "created_at": "Mon Aug 05 20:47:28 +0000 2013", "contributors_enabled": false, "time_zone": "Atlantic Time (Canada)", "profile_sidebar_border_color": "000000", "default_profile": false, "following": false, "listed_count": 4}