{"contributors": null, "truncated": false, "text": "Puberty hit Maddie so hard http://t.co/twF2h86z3A", "in_reply_to_status_id": null, "id": 459061109937680384, "favorite_count": 3, "source": "<a href=\"http://twitter.com/download/iphone\" rel=\"nofollow\">Twitter for iPhone</a>", "retweeted": false, "coordinates": null, "entities": {"symbols": [], "user_mentions": [], "hashtags": [], "urls": [], "media": [{"expanded_url": "http://twitter.com/thegodvato/status/459061109937680384/photo/1", "sizes": {"small": {"h": 340, "w": 340, "resize": "fit"}, "large": {"h": 600, "w": 600, "resize": "fit"}, "medium": {"h": 600, "w": 600, "resize": "fit"}, "thumb": {"h": 150, "w": 150, "resize": "crop"}}, "url": "http://t.co/twF2h86z3A", "media_url_https": "https://pbs.twimg.com/media/Bl7ppXTIgAEDQeQ.jpg", "id_str": "459061108876541953", "indices": [27, 49], "media_url": "http://pbs.twimg.com/media/Bl7ppXTIgAEDQeQ.jpg", "type": "photo", "id": 459061108876541953, "display_url": "pic.twitter.com/twF2h86z3A"}]}, "in_reply_to_screen_name": null, "id_str": "459061109937680384", "retweet_count": 5, "in_reply_to_user_id": null, "favorited": false, "user": {"follow_request_sent": false, "profile_use_background_image": true, "id": 269495237, "verified": false, "profile_text_color": "FC97DC", "profile_image_url_https": "https://pbs.twimg.com/profile_images/458989895730876416/7PJ5hgrc_normal.jpeg", "profile_sidebar_fill_color": "000000", "is_translator": false, "geo_enabled": false, "entities": {"url": {"urls": [{"url": "http://t.co/4e8aFGQSHE", "indices": [0, 22], "expanded_url": "http://smarturl.it/buyNeonLights", "display_url": "smarturl.it/buyNeonLights"}]}, "description": {"urls": []}}, "followers_count": 3105, "protected": false, "location": "demi's booty ", "default_profile_image": false, "id_str": "269495237", "lang": "en", "utc_offset": -18000, "statuses_count": 5752, "description": "GET A LIFE YOU IGNORANT FUCKS daughter of demi lovato and zayn malik byE", "friends_count": 337, "profile_link_color": "FF24A0", "profile_image_url": "http://pbs.twimg.com/profile_images/458989895730876416/7PJ5hgrc_normal.jpeg", "notifications": false, "profile_background_image_url_https": "https://pbs.twimg.com/profile_background_images/455790806394097665/c90dQa-s.jpeg", "profile_background_color": "FAADE9", "profile_banner_url": "https://pbs.twimg.com/profile_banners/269495237/1397471720", "profile_background_image_url": "http://pbs.twimg.com/profile_background_images/455790806394097665/c90dQa-s.jpeg", "name": "P\u271d ", "is_translation_enabled": false, "profile_background_tile": true, "favourites_count": 781, "screen_name": "thegodvato", "url": "http://t.co/4e8aFGQSHE", "created_at": "Sun Mar 20 22:17:22 +0000 2011", "contributors_enabled": false, "time_zone": "Quito", "profile_sidebar_border_color": "FFFFFF", "default_profile": false, "following": false, "listed_count": 15}, "geo": null, "in_reply_to_user_id_str": null, "possibly_sensitive": false, "lang": "en", "created_at": "Wed Apr 23 20:07:52 +0000 2014", "in_reply_to_status_id_str": null, "place": null}