{"follow_request_sent": null, "profile_use_background_image": true, "id": 25051933, "verified": false, "profile_image_url_https": "https://pbs.twimg.com/profile_images/433315760279412736/TF5YgW5V_normal.jpeg", "profile_sidebar_fill_color": "F7DA93", "is_translator": false, "geo_enabled": false, "profile_text_color": "000000", "followers_count": 257, "protected": false, "location": "Durban, RSA", "default_profile_image": false, "id_str": "25051933", "lang": "en", "utc_offset": 3600, "statuses_count": 7272, "description": "Wardell Insurance Brokers.                                                                           BTF L2 Coach.Enjoy doing Iron-distiance races,LOVE raisins!", "friends_count": 102, "profile_link_color": "CC3300", "profile_image_url": "http://pbs.twimg.com/profile_images/433315760279412736/TF5YgW5V_normal.jpeg", "notifications": null, "profile_background_image_url_https": "https://pbs.twimg.com/profile_background_images/194971258/Outlaw_Finish.jpg", "profile_background_color": "000000", "profile_banner_url": "https://pbs.twimg.com/profile_banners/25051933/1351630882", "profile_background_image_url": "http://pbs.twimg.com/profile_background_images/194971258/Outlaw_Finish.jpg", "screen_name": "JamieWardell", "is_translation_enabled": false, "profile_background_tile": false, "favourites_count": 69, "name": "Jamie Wardell", "url": null, "created_at": "Wed Mar 18 10:03:56 +0000 2009", "contributors_enabled": false, "time_zone": "London", "profile_sidebar_border_color": "000000", "default_profile": false, "following": null, "listed_count": 6}