{"follow_request_sent": null, "profile_use_background_image": true, "id": 1400282226, "verified": false, "profile_image_url_https": "https://pbs.twimg.com/profile_images/454646878349832193/kKQO47H0_normal.jpeg", "profile_sidebar_fill_color": "DDEEF6", "is_translator": false, "geo_enabled": true, "profile_text_color": "333333", "followers_count": 2475, "protected": false, "location": "Ukraine", "default_profile_image": false, "id_str": "1400282226", "lang": "ru", "utc_offset": null, "statuses_count": 16443, "description": "#\u043b\u0430\u0440\u0440\u0438 #\u0434\u0438\u0440\u0435\u043a\u0448\u0438\u043e\u043d\u0435\u0440 #\u0431\u0435\u043b\u0438\u0431\u0435\u0440 #swiftie #RihannaNavy #\u043b\u043e\u0432\u0430\u0442\u0438\u043a #\u0434\u0432 #\u0441\u043b\u044d\u0448\u0435\u0440 #Gleek \u041c\u041e\u042f \u041b\u042e\u0411\u041e\u0412\u042c- @sun_anna69", "friends_count": 2122, "profile_link_color": "174FBF", "profile_image_url": "http://pbs.twimg.com/profile_images/454646878349832193/kKQO47H0_normal.jpeg", "notifications": null, "profile_background_image_url_https": "https://pbs.twimg.com/profile_background_images/454652121384624128/6XPsv8Lm.jpeg", "profile_background_color": "F01D47", "profile_banner_url": "https://pbs.twimg.com/profile_banners/1400282226/1397231513", "profile_background_image_url": "http://pbs.twimg.com/profile_background_images/454652121384624128/6XPsv8Lm.jpeg", "screen_name": "marussia888", "is_translation_enabled": false, "profile_background_tile": true, "favourites_count": 1367, "name": "\u0412\u0410\u041d\u0418\u041b\u042c\u041d\u0410\u042f \u041a\u0423\u0420\u0418\u0426\u0410", "url": "http://instagram.com/marussia69", "created_at": "Fri May 03 17:42:40 +0000 2013", "contributors_enabled": false, "time_zone": null, "profile_sidebar_border_color": "000000", "default_profile": false, "following": null, "listed_count": 8}