{"contributors": null, "truncated": false, "text": "#EstuVBC Txus: \"Los resultados no son malos, pero podr\u00edan ser mejores. Eso nos har\u00eda dejar de mirar solo hacia atr\u00e1s.\"", "in_reply_to_status_id": null, "id": 457952110316097536, "favorite_count": 0, "source": "<a href=\"http://twitter.com/#!/download/ipad\" rel=\"nofollow\">Twitter for iPad</a>", "retweeted": false, "coordinates": null, "entities": {"symbols": [], "user_mentions": [], "hashtags": [{"indices": [0, 8], "text": "EstuVBC"}], "urls": []}, "in_reply_to_screen_name": null, "id_str": "457952110316097536", "retweet_count": 0, "in_reply_to_user_id": null, "favorited": false, "user": {"follow_request_sent": false, "profile_use_background_image": true, "id": 19781359, "verified": true, "profile_text_color": "002D71", "profile_image_url_https": "https://pbs.twimg.com/profile_images/422076538410901504/hk5MnliZ_normal.jpeg", "profile_sidebar_fill_color": "0085D7", "is_translator": false, "geo_enabled": true, "entities": {"url": {"urls": [{"url": "http://t.co/o7IZOrdD2E", "indices": [0, 22], "expanded_url": "http://www.clubestudiantes.com", "display_url": "clubestudiantes.com"}]}, "description": {"urls": []}}, "followers_count": 21603, "protected": false, "location": "C/ Serrano 127, Madrid, Spain", "default_profile_image": false, "id_str": "19781359", "lang": "es", "utc_offset": 7200, "statuses_count": 22471, "description": "@Tuenti_Movil Estudiantes, desde 1948 formando personas a trav\u00e9s del baloncesto. Competimos en @acbcom , #LF2, #EBA y #cantera", "friends_count": 3028, "profile_link_color": "004CA8", "profile_image_url": "http://pbs.twimg.com/profile_images/422076538410901504/hk5MnliZ_normal.jpeg", "notifications": false, "profile_background_image_url_https": "https://pbs.twimg.com/profile_background_images/378800000166456390/tZdbhObl.jpeg", "profile_background_color": "A31D22", "profile_banner_url": "https://pbs.twimg.com/profile_banners/19781359/1389465874", "profile_background_image_url": "http://pbs.twimg.com/profile_background_images/378800000166456390/tZdbhObl.jpeg", "name": "Tuenti M Estudiantes", "is_translation_enabled": false, "profile_background_tile": false, "favourites_count": 173, "screen_name": "ClubEstudiantes", "url": "http://t.co/o7IZOrdD2E", "created_at": "Fri Jan 30 18:49:16 +0000 2009", "contributors_enabled": false, "time_zone": "Madrid", "profile_sidebar_border_color": "FFFFFF", "default_profile": false, "following": false, "listed_count": 572}, "geo": null, "in_reply_to_user_id_str": null, "lang": "es", "created_at": "Sun Apr 20 18:41:06 +0000 2014", "in_reply_to_status_id_str": null, "place": null}