{"follow_request_sent": null, "profile_use_background_image": true, "id": 966567541, "verified": false, "profile_image_url_https": "https://pbs.twimg.com/profile_images/435511218544345090/WI_wjuQI_normal.jpeg", "profile_sidebar_fill_color": "DDEEF6", "is_translator": false, "geo_enabled": false, "profile_text_color": "333333", "followers_count": 624, "protected": false, "location": "", "default_profile_image": false, "id_str": "966567541", "lang": "fr", "utc_offset": 7200, "statuses_count": 26451, "description": "Airhead // #twitteraddicted // loves talking // bro&sis: love them all~ // and of course LOVE ANIMEE !!", "friends_count": 608, "profile_link_color": "0084B4", "profile_image_url": "http://pbs.twimg.com/profile_images/435511218544345090/WI_wjuQI_normal.jpeg", "notifications": null, "profile_background_image_url_https": "https://pbs.twimg.com/profile_background_images/451446461851389952/arvq4fD3.jpeg", "profile_background_color": "C0DEED", "profile_banner_url": "https://pbs.twimg.com/profile_banners/966567541/1388182402", "profile_background_image_url": "http://pbs.twimg.com/profile_background_images/451446461851389952/arvq4fD3.jpeg", "screen_name": "Sonzali", "is_translation_enabled": false, "profile_background_tile": false, "favourites_count": 4397, "name": "Magic Star", "url": null, "created_at": "Fri Nov 23 17:59:43 +0000 2012", "contributors_enabled": false, "time_zone": "Amsterdam", "profile_sidebar_border_color": "FFFFFF", "default_profile": false, "following": null, "listed_count": 5}