{"contributors": null, "truncated": false, "text": "vado a nanna. #off", "in_reply_to_status_id": null, "id": 459794315594964993, "favorite_count": 1, "source": "<a href=\"http://twitter.com/download/android\" rel=\"nofollow\">Twitter for Android</a>", "retweeted": false, "coordinates": null, "entities": {"symbols": [], "user_mentions": [], "hashtags": [{"indices": [14, 18], "text": "off"}], "urls": []}, "in_reply_to_screen_name": null, "id_str": "459794315594964993", "retweet_count": 0, "in_reply_to_user_id": null, "favorited": false, "user": {"follow_request_sent": false, "profile_use_background_image": true, "id": 2483530427, "verified": false, "profile_text_color": "333333", "profile_image_url_https": "https://pbs.twimg.com/profile_images/458243083935948800/v6yCRVzM_normal.jpeg", "profile_sidebar_fill_color": "DDEEF6", "is_translator": false, "geo_enabled": false, "entities": {"description": {"urls": []}}, "followers_count": 886, "protected": false, "location": "-matthias xzavier harris.-", "default_profile_image": false, "id_str": "2483530427", "lang": "it", "utc_offset": null, "statuses_count": 3380, "description": "the world is full of monsters with friendly faces.", "friends_count": 1041, "profile_link_color": "565C5E", "profile_image_url": "http://pbs.twimg.com/profile_images/458243083935948800/v6yCRVzM_normal.jpeg", "notifications": false, "profile_background_image_url_https": "https://pbs.twimg.com/profile_background_images/455636140029009920/0vSJ2JQr.png", "profile_background_color": "FFFFFF", "profile_banner_url": "https://pbs.twimg.com/profile_banners/2483530427/1398088638", "profile_background_image_url": "http://pbs.twimg.com/profile_background_images/455636140029009920/0vSJ2JQr.png", "name": "matthias. ", "is_translation_enabled": false, "profile_background_tile": true, "favourites_count": 6254, "screen_name": "matthiasgdr", "url": null, "created_at": "Mon Apr 14 07:07:25 +0000 2014", "contributors_enabled": false, "time_zone": null, "profile_sidebar_border_color": "FFFFFF", "default_profile": false, "following": false, "listed_count": 1}, "geo": null, "in_reply_to_user_id_str": null, "lang": "pt", "created_at": "Fri Apr 25 20:41:22 +0000 2014", "in_reply_to_status_id_str": null, "place": null}