{"contributors": null, "truncated": false, "text": "RT @iamanart: \u201c\u0e09\u0e31\u0e19\u0e2d\u0e22\u0e39\u0e48\u0e17\u0e35\u0e48\u0e19\u0e35\u0e48\u0e44\u0e21\u0e48\u0e44\u0e14\u0e49\u0e41\u0e25\u0e49\u0e27 ... \u0e19\u0e32\u0e22\u0e08\u0e30\u0e2d\u0e22\u0e39\u0e48\u0e44\u0e14\u0e49\u0e23\u0e36\u0e40\u0e1b\u0e25\u0e48\u0e32 \u0e16\u0e49\u0e32\u0e09\u0e31\u0e19\u0e44\u0e21\u0e48\u0e2d\u0e22\u0e39\u0e48\u0e41\u0e25\u0e49\u0e27?\u201d #Doraemon3D #\u0e21\u0e2b\u0e01\u0e23\u0e23\u0e21\u0e40\u0e25\u0e48\u0e19\u0e21\u0e37\u0e2d\u0e16\u0e37\u0e2d\u0e2d\u0e22\u0e39\u0e48\u0e14\u0e35\u0e46\u0e19\u0e49\u0e33\u0e15\u0e32\u0e01\u0e47\u0e44\u0e2b\u0e25 http://t.\u2026", "in_reply_to_status_id": null, "id": 458637893230014464, "favorite_count": 0, "source": "<a href=\"http://twitter.com/download/android\" rel=\"nofollow\">Twitter for Android</a>", "retweeted": false, "coordinates": null, "entities": {"symbols": [], "user_mentions": [{"indices": [3, 12], "screen_name": "iamanart", "id": 334696668, "name": "IAMANART.", "id_str": "334696668"}], "hashtags": [{"indices": [83, 94], "text": "Doraemon3D"}, {"indices": [95, 129], "text": "\u0e21\u0e2b\u0e01\u0e23\u0e23\u0e21\u0e40\u0e25\u0e48\u0e19\u0e21\u0e37\u0e2d\u0e16\u0e37\u0e2d\u0e2d\u0e22\u0e39\u0e48\u0e14\u0e35\u0e46\u0e19\u0e49\u0e33\u0e15\u0e32\u0e01\u0e47\u0e44\u0e2b\u0e25"}], "urls": [], "media": [{"expanded_url": "http://twitter.com/iamanart/status/458502853674299392/photo/1", "sizes": {"small": {"h": 191, "w": 339, "resize": "fit"}, "large": {"h": 576, "w": 1024, "resize": "fit"}, "medium": {"h": 337, "w": 599, "resize": "fit"}, "thumb": {"h": 150, "w": 150, "resize": "crop"}}, "url": "http://t.co/dhBrUVkTTc", "media_url_https": "https://pbs.twimg.com/media/Blzt6n7CIAA0g2Z.jpg", "id_str": "458502853489729536", "indices": [139, 140], "media_url": "http://pbs.twimg.com/media/Blzt6n7CIAA0g2Z.jpg", "type": "photo", "id": 458502853489729536, "display_url": "pic.twitter.com/dhBrUVkTTc"}]}, "in_reply_to_screen_name": null, "id_str": "458637893230014464", "retweet_count": 3032, "in_reply_to_user_id": null, "favorited": false, "retweeted_status": {"contributors": null, "truncated": false, "text": "\u201c\u0e09\u0e31\u0e19\u0e2d\u0e22\u0e39\u0e48\u0e17\u0e35\u0e48\u0e19\u0e35\u0e48\u0e44\u0e21\u0e48\u0e44\u0e14\u0e49\u0e41\u0e25\u0e49\u0e27 ... \u0e19\u0e32\u0e22\u0e08\u0e30\u0e2d\u0e22\u0e39\u0e48\u0e44\u0e14\u0e49\u0e23\u0e36\u0e40\u0e1b\u0e25\u0e48\u0e32 \u0e16\u0e49\u0e32\u0e09\u0e31\u0e19\u0e44\u0e21\u0e48\u0e2d\u0e22\u0e39\u0e48\u0e41\u0e25\u0e49\u0e27?\u201d #Doraemon3D #\u0e21\u0e2b\u0e01\u0e23\u0e23\u0e21\u0e40\u0e25\u0e48\u0e19\u0e21\u0e37\u0e2d\u0e16\u0e37\u0e2d\u0e2d\u0e22\u0e39\u0e48\u0e14\u0e35\u0e46\u0e19\u0e49\u0e33\u0e15\u0e32\u0e01\u0e47\u0e44\u0e2b\u0e25 http://t.co/dhBrUVkTTc", "in_reply_to_status_id": null, "id": 458502853674299392, "favorite_count": 312, "source": "<a href=\"http://www.twitter.com\" rel=\"nofollow\">Twitter for Windows Phone</a>", "retweeted": false, "coordinates": null, "entities": {"symbols": [], "user_mentions": [], "hashtags": [{"indices": [69, 80], "text": "Doraemon3D"}, {"indices": [81, 115], "text": "\u0e21\u0e2b\u0e01\u0e23\u0e23\u0e21\u0e40\u0e25\u0e48\u0e19\u0e21\u0e37\u0e2d\u0e16\u0e37\u0e2d\u0e2d\u0e22\u0e39\u0e48\u0e14\u0e35\u0e46\u0e19\u0e49\u0e33\u0e15\u0e32\u0e01\u0e47\u0e44\u0e2b\u0e25"}], "urls": [], "media": [{"expanded_url": "http://twitter.com/iamanart/status/458502853674299392/photo/1", "sizes": {"small": {"h": 191, "w": 339, "resize": "fit"}, "large": {"h": 576, "w": 1024, "resize": "fit"}, "medium": {"h": 337, "w": 599, "resize": "fit"}, "thumb": {"h": 150, "w": 150, "resize": "crop"}}, "url": "http://t.co/dhBrUVkTTc", "media_url_https": "https://pbs.twimg.com/media/Blzt6n7CIAA0g2Z.jpg", "id_str": "458502853489729536", "indices": [116, 138], "media_url": "http://pbs.twimg.com/media/Blzt6n7CIAA0g2Z.jpg", "type": "photo", "id": 458502853489729536, "display_url": "pic.twitter.com/dhBrUVkTTc"}]}, "in_reply_to_screen_name": null, "id_str": "458502853674299392", "retweet_count": 3032, "in_reply_to_user_id": null, "favorited": false, "user": {"follow_request_sent": false, "profile_use_background_image": false, "id": 334696668, "verified": false, "profile_text_color": "666666", "profile_image_url_https": "https://pbs.twimg.com/profile_images/456452309044559873/DRNDaDwP_normal.jpeg", "profile_sidebar_fill_color": "252429", "is_translator": false, "geo_enabled": true, "entities": {"description": {"urls": []}}, "followers_count": 149, "protected": false, "location": "", "default_profile_image": false, "id_str": "334696668", "lang": "en", "utc_offset": 25200, "statuses_count": 21059, "description": "twitter is thing that i'm thinking and doing.", "friends_count": 72, "profile_link_color": "FF3C00", "profile_image_url": "http://pbs.twimg.com/profile_images/456452309044559873/DRNDaDwP_normal.jpeg", "notifications": false, "profile_background_image_url_https": "https://pbs.twimg.com/profile_background_images/378800000169757911/fdhqGRyg.jpeg", "profile_background_color": "1A1B1F", "profile_background_image_url": "http://pbs.twimg.com/profile_background_images/378800000169757911/fdhqGRyg.jpeg", "name": "IAMANART.", "is_translation_enabled": false, "profile_background_tile": false, "favourites_count": 180, "screen_name": "iamanart", "url": null, "created_at": "Wed Jul 13 14:37:21 +0000 2011", "contributors_enabled": false, "time_zone": "Bangkok", "profile_sidebar_border_color": "000000", "default_profile": false, "following": false, "listed_count": 0}, "geo": null, "in_reply_to_user_id_str": null, "possibly_sensitive": false, "lang": "th", "created_at": "Tue Apr 22 07:09:33 +0000 2014", "in_reply_to_status_id_str": null, "place": null}, "user": {"follow_request_sent": false, "profile_use_background_image": true, "id": 392677885, "verified": false, "profile_text_color": "333333", "profile_image_url_https": "https://pbs.twimg.com/profile_images/446933654787215360/f5dBvWmH_normal.jpeg", "profile_sidebar_fill_color": "EFEFEF", "is_translator": false, "geo_enabled": false, "entities": {"url": {"urls": [{"url": "http://t.co/J7y96HaDHO", "indices": [0, 22], "expanded_url": "http://www.twitter.com/jean_323", "display_url": "twitter.com/jean_323"}]}, "description": {"urls": []}}, "followers_count": 159, "protected": false, "location": "", "default_profile_image": false, "id_str": "392677885", "lang": "en", "utc_offset": 25200, "statuses_count": 15161, "description": "\u0e21\u0e19\u0e38\u0e29\u0e22\u0e4c\u0e17\u0e35\u0e48 support \u0e44\u0e14\u0e49\u0e2b\u0e25\u0e32\u0e22\u0e2d\u0e22\u0e48\u0e32\u0e07 \u0e40\u0e1b\u0e47\u0e19 Shawol #\uc0e4\uc774\ub2c8 \u0e41\u0e15\u0e48\u0e0a\u0e2d\u0e1a AF8 \u0e0a\u0e35\u0e27\u0e34\u0e15\u0e19\u0e35\u0e49\u0e15\u0e34\u0e14 VRZO \u0e22\u0e34\u0e48\u0e07\u0e01\u0e27\u0e48\u0e32\u0e2d\u0e30\u0e44\u0e23 \u0e2a\u0e16\u0e32\u0e19\u0e30: WHY SO SERIOUS? \u25c7Support:SHINee,VRZO,AF8\u25c7", "friends_count": 444, "profile_link_color": "4FE3BC", "profile_image_url": "http://pbs.twimg.com/profile_images/446933654787215360/f5dBvWmH_normal.jpeg", "notifications": false, "profile_background_image_url_https": "https://abs.twimg.com/images/themes/theme18/bg.gif", "profile_background_color": "C9E0DC", "profile_banner_url": "https://pbs.twimg.com/profile_banners/392677885/1395392258", "profile_background_image_url": "http://abs.twimg.com/images/themes/theme18/bg.gif", "name": "L o a d i n g . . .", "is_translation_enabled": false, "profile_background_tile": false, "favourites_count": 718, "screen_name": "jean_323", "url": "http://t.co/J7y96HaDHO", "created_at": "Mon Oct 17 12:13:31 +0000 2011", "contributors_enabled": false, "time_zone": "Bangkok", "profile_sidebar_border_color": "FFFFFF", "default_profile": false, "following": false, "listed_count": 0}, "geo": null, "in_reply_to_user_id_str": null, "possibly_sensitive": false, "lang": "th", "created_at": "Tue Apr 22 16:06:09 +0000 2014", "in_reply_to_status_id_str": null, "place": null}