{"follow_request_sent": null, "profile_use_background_image": true, "id": 550433057, "verified": false, "profile_image_url_https": "https://pbs.twimg.com/profile_images/451519578334851072/fJnTS65r_normal.jpeg", "profile_sidebar_fill_color": "DDEEF6", "is_translator": false, "geo_enabled": false, "profile_text_color": "333333", "followers_count": 535, "protected": false, "location": "", "default_profile_image": false, "id_str": "550433057", "lang": "en", "utc_offset": -10800, "statuses_count": 14530, "description": "Dancer. Model. Cheerleader. Instagram : @gabbiefernandez", "friends_count": 343, "profile_link_color": "0084B4", "profile_image_url": "http://pbs.twimg.com/profile_images/451519578334851072/fJnTS65r_normal.jpeg", "notifications": null, "profile_background_image_url_https": "https://pbs.twimg.com/profile_background_images/451717857760382976/3Gfaytsu.jpeg", "profile_background_color": "C0DEED", "profile_banner_url": "https://pbs.twimg.com/profile_banners/550433057/1398036215", "profile_background_image_url": "http://pbs.twimg.com/profile_background_images/451717857760382976/3Gfaytsu.jpeg", "screen_name": "gabbiefernandez", "is_translation_enabled": false, "profile_background_tile": true, "favourites_count": 2726, "name": "Gabbie Fernandez ", "url": null, "created_at": "Tue Apr 10 20:48:02 +0000 2012", "contributors_enabled": false, "time_zone": "Atlantic Time (Canada)", "profile_sidebar_border_color": "FFFFFF", "default_profile": false, "following": null, "listed_count": 2}