{"contributors": null, "truncated": false, "text": "RT @StateDept: On April 22, @JohnKerry and @RajShah deliver remarks at the #QDDR Launch with @HHigginbottom and @TomPerriello. http://t.co/\u2026", "in_reply_to_status_id": null, "id": 458272604584148994, "favorite_count": 0, "source": "<a href=\"https://about.twitter.com/products/tweetdeck\" rel=\"nofollow\">TweetDeck</a>", "retweeted": false, "coordinates": null, "entities": {"symbols": [], "user_mentions": [{"indices": [3, 13], "screen_name": "StateDept", "id": 9624742, "name": "Department of State", "id_str": "9624742"}, {"indices": [28, 38], "screen_name": "JohnKerry", "id": 15007149, "name": "John Kerry", "id_str": "15007149"}, {"indices": [43, 51], "screen_name": "rajshah", "id": 232193350, "name": "Raj Shah", "id_str": "232193350"}, {"indices": [93, 107], "screen_name": "hhigginbottom", "id": 210206603, "name": "Heather Higginbottom", "id_str": "210206603"}, {"indices": [112, 125], "screen_name": "tomperriello", "id": 14384907, "name": "Tom Perriello", "id_str": "14384907"}], "hashtags": [{"indices": [75, 80], "text": "QDDR"}], "urls": [{"url": "http://t.co/XcFyHtaUeh", "indices": [139, 140], "expanded_url": "http://go.usa.gov/kRnT", "display_url": "go.usa.gov/kRnT"}]}, "in_reply_to_screen_name": null, "id_str": "458272604584148994", "retweet_count": 17, "in_reply_to_user_id": null, "favorited": false, "retweeted_status": {"contributors": null, "truncated": false, "text": "On April 22, @JohnKerry and @RajShah deliver remarks at the #QDDR Launch with @HHigginbottom and @TomPerriello. http://t.co/XcFyHtaUeh", "in_reply_to_status_id": null, "id": 458266871331303424, "favorite_count": 9, "source": "web", "retweeted": false, "coordinates": null, "entities": {"symbols": [], "user_mentions": [{"indices": [13, 23], "screen_name": "JohnKerry", "id": 15007149, "name": "John Kerry", "id_str": "15007149"}, {"indices": [28, 36], "screen_name": "rajshah", "id": 232193350, "name": "Raj Shah", "id_str": "232193350"}, {"indices": [78, 92], "screen_name": "hhigginbottom", "id": 210206603, "name": "Heather Higginbottom", "id_str": "210206603"}, {"indices": [97, 110], "screen_name": "tomperriello", "id": 14384907, "name": "Tom Perriello", "id_str": "14384907"}], "hashtags": [{"indices": [60, 65], "text": "QDDR"}], "urls": [{"url": "http://t.co/XcFyHtaUeh", "indices": [112, 134], "expanded_url": "http://go.usa.gov/kRnT", "display_url": "go.usa.gov/kRnT"}]}, "in_reply_to_screen_name": null, "id_str": "458266871331303424", "retweet_count": 17, "in_reply_to_user_id": null, "favorited": false, "user": {"follow_request_sent": false, "profile_use_background_image": true, "id": 9624742, "verified": true, "profile_text_color": "000000", "profile_image_url_https": "https://pbs.twimg.com/profile_images/420238587381043200/N0Xzt_no_normal.jpeg", "profile_sidebar_fill_color": "DEDACB", "is_translator": false, "geo_enabled": false, "entities": {"url": {"urls": [{"url": "http://t.co/eFqP1Dh9U9", "indices": [0, 22], "expanded_url": "http://www.state.gov", "display_url": "state.gov"}]}, "description": {"urls": []}}, "followers_count": 877985, "protected": false, "location": "Washington, DC", "default_profile_image": false, "id_str": "9624742", "lang": "en", "utc_offset": -14400, "statuses_count": 31510, "description": "Welcome to the official U.S. Department of State Twitter account!  \nSecretary Kerry tweets from @JohnKerry.", "friends_count": 355, "profile_link_color": "3975AD", "profile_image_url": "http://pbs.twimg.com/profile_images/420238587381043200/N0Xzt_no_normal.jpeg", "notifications": false, "profile_background_image_url_https": "https://pbs.twimg.com/profile_background_images/378800000163620045/hKZbIxos.jpeg", "profile_background_color": "184266", "profile_banner_url": "https://pbs.twimg.com/profile_banners/9624742/1355339362", "profile_background_image_url": "http://pbs.twimg.com/profile_background_images/378800000163620045/hKZbIxos.jpeg", "name": "Department of State", "is_translation_enabled": false, "profile_background_tile": false, "favourites_count": 3, "screen_name": "StateDept", "url": "http://t.co/eFqP1Dh9U9", "created_at": "Tue Oct 23 15:02:45 +0000 2007", "contributors_enabled": false, "time_zone": "Eastern Time (US & Canada)", "profile_sidebar_border_color": "FFFFFF", "default_profile": false, "following": false, "listed_count": 14273}, "geo": null, "in_reply_to_user_id_str": null, "possibly_sensitive": false, "lang": "en", "created_at": "Mon Apr 21 15:31:50 +0000 2014", "in_reply_to_status_id_str": null, "place": null}, "user": {"follow_request_sent": false, "profile_use_background_image": true, "id": 210206603, "verified": true, "profile_text_color": "333333", "profile_image_url_https": "https://pbs.twimg.com/profile_images/451393944635457536/zBq5KBCq_normal.jpeg", "profile_sidebar_fill_color": "DDEEF6", "is_translator": false, "geo_enabled": false, "entities": {"url": {"urls": [{"url": "http://t.co/HXJf5nOrcz", "indices": [0, 22], "expanded_url": "http://state.gov", "display_url": "state.gov"}]}, "description": {"urls": []}}, "followers_count": 1848, "protected": false, "location": "", "default_profile_image": false, "id_str": "210206603", "lang": "en", "utc_offset": -10800, "statuses_count": 50, "description": "Deputy Secretary of @StateDept", "friends_count": 223, "profile_link_color": "3975AD", "profile_image_url": "http://pbs.twimg.com/profile_images/451393944635457536/zBq5KBCq_normal.jpeg", "notifications": false, "profile_background_image_url_https": "https://pbs.twimg.com/profile_background_images/451390297335799808/5S7gvPgT.jpeg", "profile_background_color": "184266", "profile_banner_url": "https://pbs.twimg.com/profile_banners/210206603/1396535405", "profile_background_image_url": "http://pbs.twimg.com/profile_background_images/451390297335799808/5S7gvPgT.jpeg", "name": "Heather Higginbottom", "is_translation_enabled": false, "profile_background_tile": false, "favourites_count": 34, "screen_name": "hhigginbottom", "url": "http://t.co/HXJf5nOrcz", "created_at": "Sat Oct 30 20:58:20 +0000 2010", "contributors_enabled": false, "time_zone": "Atlantic Time (Canada)", "profile_sidebar_border_color": "FFFFFF", "default_profile": false, "following": false, "listed_count": 27}, "geo": null, "in_reply_to_user_id_str": null, "possibly_sensitive": false, "lang": "en", "created_at": "Mon Apr 21 15:54:37 +0000 2014", "in_reply_to_status_id_str": null, "place": null}