{"follow_request_sent": false, "profile_use_background_image": true, "time_zone": "London", "id": 24960287, "verified": true, "profile_text_color": "333333", "muting": false, "profile_image_url_https": "https://pbs.twimg.com/profile_images/378800000418530007/c7e7f2ae6edd9ee48c55823a2942a044_normal.png", "profile_sidebar_fill_color": "DDEEF6", "is_translator": false, "geo_enabled": false, "entities": {"url": {"urls": [{"url": "http://t.co/2FPDqrkc0o", "indices": [0, 22], "expanded_url": "http://www.dominiclittlewood.com", "display_url": "dominiclittlewood.com"}]}, "description": {"urls": []}}, "followers_count": 4291, "protected": false, "id_str": "24960287", "default_profile_image": false, "listed_count": 26, "status": {"lang": "en", "favorited": false, "in_reply_to_user_id": 21244068, "contributors": null, "truncated": false, "text": ".@sammy1983 @vfestival If you used a credit card and the bill was more than \u00a3100 you're covered by the consumer Credit Act section 75", "created_at": "Fri Apr 25 18:17:35 +0000 2014", "retweeted": false, "in_reply_to_status_id": 459738641170833410, "coordinates": null, "id": 459758134391611392, "entities": {"symbols": [], "user_mentions": [{"indices": [1, 11], "screen_name": "sammy1983", "id": 21244068, "name": "sammy randle", "id_str": "21244068"}, {"indices": [12, 22], "screen_name": "vfestival", "id": 25990962, "name": "V FESTIVAL", "id_str": "25990962"}], "hashtags": [], "urls": []}, "in_reply_to_status_id_str": "459738641170833410", "in_reply_to_screen_name": "sammy1983", "source": "<a href=\"http://twitter.com/tweetbutton\" rel=\"nofollow\">Tweet Button</a>", "place": null, "retweet_count": 0, "geo": null, "in_reply_to_user_id_str": "21244068", "favorite_count": 0, "id_str": "459758134391611392"}, "lang": "en", "utc_offset": 3600, "statuses_count": 314, "description": "New series of Beware Cowboy Builders Thursdays 20.00 Ch5.", "friends_count": 70, "profile_link_color": "0084B4", "profile_image_url": "http://pbs.twimg.com/profile_images/378800000418530007/c7e7f2ae6edd9ee48c55823a2942a044_normal.png", "notifications": false, "profile_background_image_url_https": "https://abs.twimg.com/images/themes/theme1/bg.png", "profile_background_color": "C0DEED", "profile_background_image_url": "http://abs.twimg.com/images/themes/theme1/bg.png", "name": "Dominic Littlewood", "is_translation_enabled": false, "profile_background_tile": false, "favourites_count": 18, "screen_name": "DomLittlewood", "url": "http://t.co/2FPDqrkc0o", "created_at": "Tue Mar 17 21:37:05 +0000 2009", "contributors_enabled": false, "location": "Hamstead, London NW3", "profile_sidebar_border_color": "C0DEED", "default_profile": true, "following": false}