{"follow_request_sent": false, "profile_use_background_image": true, "id": 33915734, "verified": true, "profile_text_color": "8C8481", "profile_image_url_https": "https://pbs.twimg.com/profile_images/446261557568090112/1RKYLC_e_normal.jpeg", "profile_sidebar_fill_color": "F7F6D2", "is_translator": false, "geo_enabled": true, "entities": {"url": {"urls": [{"url": "http://t.co/81k6AWVJo6", "indices": [0, 22], "expanded_url": "http://www.glamour.es/", "display_url": "glamour.es"}]}, "description": {"urls": []}}, "followers_count": 114599, "protected": false, "location": "Spain ", "default_profile_image": false, "id_str": "33915734", "status": {"contributors": null, "truncated": false, "text": "Aprovechamos el \u00e9xodo masivo para disfrutar de las citas culturales Glamour \u00a1sin colas! http://t.co/foUCJPrBAF", "in_reply_to_status_id": null, "id": 457443936089686016, "favorite_count": 3, "source": "<a href=\"http://www.hootsuite.com\" rel=\"nofollow\">HootSuite</a>", "retweeted": false, "coordinates": null, "entities": {"symbols": [], "user_mentions": [], "hashtags": [], "urls": [{"url": "http://t.co/foUCJPrBAF", "indices": [88, 110], "expanded_url": "http://ow.ly/vQtKn", "display_url": "ow.ly/vQtKn"}]}, "in_reply_to_screen_name": null, "id_str": "457443936089686016", "retweet_count": 0, "in_reply_to_user_id": null, "favorited": false, "geo": null, "in_reply_to_user_id_str": null, "possibly_sensitive": false, "lang": "es", "created_at": "Sat Apr 19 09:01:47 +0000 2014", "in_reply_to_status_id_str": null, "place": null}, "lang": "es", "utc_offset": -7200, "statuses_count": 16907, "description": "El Twitter Oficial de la Revista Glamour Espa\u00f1a", "friends_count": 268, "profile_link_color": "E80E56", "profile_image_url": "http://pbs.twimg.com/profile_images/446261557568090112/1RKYLC_e_normal.jpeg", "notifications": false, "profile_background_image_url_https": "https://pbs.twimg.com/profile_background_images/450571025617412097/hm2Rez-H.jpeg", "profile_background_color": "FFFFFF", "profile_banner_url": "https://pbs.twimg.com/profile_banners/33915734/1395232064", "profile_background_image_url": "http://pbs.twimg.com/profile_background_images/450571025617412097/hm2Rez-H.jpeg", "name": "Glamour Espa\u00f1a", "is_translation_enabled": false, "profile_background_tile": true, "favourites_count": 41, "screen_name": "GlamourSpain", "url": "http://t.co/81k6AWVJo6", "created_at": "Tue Apr 21 14:16:25 +0000 2009", "contributors_enabled": false, "time_zone": "Greenland", "profile_sidebar_border_color": "FFFFFF", "default_profile": false, "following": false, "listed_count": 1292}