{"contributors": null, "truncated": false, "text": "Alleged child molester and fugitive Loomes Wheeler,Jr. back in jail with NO BOND. http://t.co/NaOqF6zsJ0", "in_reply_to_status_id": null, "id": 457269805934858240, "favorite_count": 0, "source": "<a href=\"http://www.apple.com\" rel=\"nofollow\">iOS</a>", "retweeted": false, "coordinates": null, "entities": {"symbols": [], "user_mentions": [], "hashtags": [], "urls": [], "media": [{"expanded_url": "http://twitter.com/MichelleWESH/status/457269805934858240/photo/1", "sizes": {"large": {"h": 716, "w": 960, "resize": "fit"}, "small": {"h": 254, "w": 340, "resize": "fit"}, "medium": {"h": 448, "w": 600, "resize": "fit"}, "thumb": {"h": 150, "w": 150, "resize": "crop"}}, "url": "http://t.co/NaOqF6zsJ0", "media_url_https": "https://pbs.twimg.com/media/BliMdy9CMAAaagH.jpg", "id_str": "457269805699969024", "indices": [82, 104], "media_url": "http://pbs.twimg.com/media/BliMdy9CMAAaagH.jpg", "type": "photo", "id": 457269805699969024, "display_url": "pic.twitter.com/NaOqF6zsJ0"}]}, "in_reply_to_screen_name": null, "id_str": "457269805934858240", "retweet_count": 0, "in_reply_to_user_id": null, "favorited": false, "user": {"follow_request_sent": false, "profile_use_background_image": true, "id": 56771109, "verified": true, "profile_text_color": "333333", "profile_image_url_https": "https://pbs.twimg.com/profile_images/313502119/mom_normal.jpg", "profile_sidebar_fill_color": "DDFFCC", "is_translator": false, "geo_enabled": false, "entities": {"url": {"urls": [{"url": "http://t.co/59U1SLqkPS", "indices": [0, 22], "expanded_url": "http://wesh.com", "display_url": "wesh.com"}]}, "description": {"urls": []}}, "followers_count": 570, "protected": false, "location": "Orlando, Fla.", "default_profile_image": false, "id_str": "56771109", "lang": "en", "utc_offset": -18000, "statuses_count": 138, "description": "News Reporter for WESH 2 News. Opinions are my own, RTs not endorsements.", "friends_count": 83, "profile_link_color": "0084B4", "profile_image_url": "http://pbs.twimg.com/profile_images/313502119/mom_normal.jpg", "notifications": false, "profile_background_image_url_https": "https://pbs.twimg.com/profile_background_images/23247824/background.jpg", "profile_background_color": "9AE4E8", "profile_background_image_url": "http://pbs.twimg.com/profile_background_images/23247824/background.jpg", "name": "Michelle Meredith", "is_translation_enabled": false, "profile_background_tile": false, "favourites_count": 2, "screen_name": "MichelleWESH", "url": "http://t.co/59U1SLqkPS", "created_at": "Tue Jul 14 18:22:39 +0000 2009", "contributors_enabled": false, "time_zone": "Quito", "profile_sidebar_border_color": "BDDCAD", "default_profile": false, "following": false, "listed_count": 22}, "geo": null, "in_reply_to_user_id_str": null, "possibly_sensitive": false, "lang": "en", "created_at": "Fri Apr 18 21:29:52 +0000 2014", "in_reply_to_status_id_str": null, "place": null}