{"follow_request_sent": false, "profile_use_background_image": false, "id": 247048493, "verified": true, "profile_text_color": "333333", "profile_image_url_https": "https://pbs.twimg.com/profile_images/2771702209/2bb3fe0bd03e66a0c8119b59ce433e64_normal.jpeg", "profile_sidebar_fill_color": "DDEEF6", "is_translator": false, "geo_enabled": false, "entities": {"url": {"urls": [{"url": "http://t.co/e0973rg1i3", "indices": [0, 22], "expanded_url": "http://www.nps.gov/grba", "display_url": "nps.gov/grba"}]}, "description": {"urls": []}}, "followers_count": 2772, "protected": false, "location": "Baker, NV", "default_profile_image": false, "id_str": "247048493", "status": {"contributors": null, "truncated": false, "text": "Our national parks are kicking off National Park Week with fee-free entrance days on Saturday, April 19 and... http://t.co/IAPssbKQvr", "in_reply_to_status_id": null, "id": 457201280109142016, "favorite_count": 1, "source": "<a href=\"http://www.facebook.com/twitter\" rel=\"nofollow\">Facebook</a>", "retweeted": false, "coordinates": null, "entities": {"symbols": [], "user_mentions": [], "hashtags": [], "urls": [{"url": "http://t.co/IAPssbKQvr", "indices": [111, 133], "expanded_url": "http://fb.me/2fminAtv2", "display_url": "fb.me/2fminAtv2"}]}, "in_reply_to_screen_name": null, "id_str": "457201280109142016", "retweet_count": 0, "in_reply_to_user_id": null, "favorited": false, "geo": null, "in_reply_to_user_id_str": null, "possibly_sensitive": false, "lang": "en", "created_at": "Fri Apr 18 16:57:34 +0000 2014", "in_reply_to_status_id_str": null, "place": null}, "lang": "en", "utc_offset": -25200, "statuses_count": 239, "description": "Experience the solitude of the desert, the smell of sagebrush after a thunderstorm, the darkest of night skies, and the beauty of Lehman Caves.", "friends_count": 113, "profile_link_color": "0084B4", "profile_image_url": "http://pbs.twimg.com/profile_images/2771702209/2bb3fe0bd03e66a0c8119b59ce433e64_normal.jpeg", "notifications": false, "profile_background_image_url_https": "https://pbs.twimg.com/profile_background_images/697310102/d395d74ad5a09f01c5e9be7d30179438.jpeg", "profile_background_color": "C0DEED", "profile_background_image_url": "http://pbs.twimg.com/profile_background_images/697310102/d395d74ad5a09f01c5e9be7d30179438.jpeg", "name": "Great Basin NPS", "is_translation_enabled": false, "profile_background_tile": false, "favourites_count": 1, "screen_name": "GreatBasinNPS", "url": "http://t.co/e0973rg1i3", "created_at": "Fri Feb 04 00:11:46 +0000 2011", "contributors_enabled": false, "time_zone": "Pacific Time (US & Canada)", "profile_sidebar_border_color": "FFFFFF", "default_profile": false, "following": false, "listed_count": 101}