{"follow_request_sent": null, "profile_use_background_image": true, "id": 80782054, "verified": false, "profile_image_url_https": "https://pbs.twimg.com/profile_images/415535304565469184/Ky-lhY4W_normal.jpeg", "profile_sidebar_fill_color": "EFEFEF", "is_translator": false, "geo_enabled": true, "profile_text_color": "333333", "followers_count": 600, "protected": false, "location": "Maldives", "default_profile_image": false, "id_str": "80782054", "lang": "en", "utc_offset": -25200, "statuses_count": 9306, "description": "One n Only SiR L!M", "friends_count": 802, "profile_link_color": "B53232", "profile_image_url": "http://pbs.twimg.com/profile_images/415535304565469184/Ky-lhY4W_normal.jpeg", "notifications": null, "profile_background_image_url_https": "https://pbs.twimg.com/profile_background_images/844115242/354f33b4766d24e8e47f6e74a948354a.jpeg", "profile_background_color": "131516", "profile_banner_url": "https://pbs.twimg.com/profile_banners/80782054/1387010830", "profile_background_image_url": "http://pbs.twimg.com/profile_background_images/844115242/354f33b4766d24e8e47f6e74a948354a.jpeg", "screen_name": "Saym3s", "is_translation_enabled": false, "profile_background_tile": false, "favourites_count": 521, "name": "SiRliM", "url": "http://www.google.mv", "created_at": "Thu Oct 08 06:21:01 +0000 2009", "contributors_enabled": false, "time_zone": "Pacific Time (US & Canada)", "profile_sidebar_border_color": "FFFFFF", "default_profile": false, "following": null, "listed_count": 4}