{"contributors": null, "truncated": false, "text": "RT @n_kurtley52: Hibernation mode\ud83d\ude14", "in_reply_to_status_id": null, "id": 457947219589861378, "favorite_count": 0, "source": "<a href=\"http://twitter.com/download/iphone\" rel=\"nofollow\">Twitter for iPhone</a>", "retweeted": false, "coordinates": null, "entities": {"symbols": [], "user_mentions": [{"indices": [3, 15], "screen_name": "n_kurtley52", "id": 1420206979, "name": "\u2728", "id_str": "1420206979"}], "hashtags": [], "urls": []}, "in_reply_to_screen_name": null, "id_str": "457947219589861378", "retweet_count": 1, "in_reply_to_user_id": null, "favorited": false, "retweeted_status": {"contributors": null, "truncated": false, "text": "Hibernation mode\ud83d\ude14", "in_reply_to_status_id": null, "id": 457946446679904257, "favorite_count": 0, "source": "<a href=\"http://twitter.com/download/iphone\" rel=\"nofollow\">Twitter for iPhone</a>", "retweeted": false, "coordinates": null, "entities": {"symbols": [], "user_mentions": [], "hashtags": [], "urls": []}, "in_reply_to_screen_name": null, "id_str": "457946446679904257", "retweet_count": 1, "in_reply_to_user_id": null, "favorited": false, "user": {"follow_request_sent": false, "profile_use_background_image": true, "id": 1420206979, "verified": false, "profile_text_color": "333333", "profile_image_url_https": "https://pbs.twimg.com/profile_images/450286164642000896/ubXyxex5_normal.jpeg", "profile_sidebar_fill_color": "F6F6F6", "is_translator": false, "geo_enabled": false, "entities": {"description": {"urls": []}}, "followers_count": 1157, "protected": false, "location": "#416", "default_profile_image": false, "id_str": "1420206979", "lang": "en", "utc_offset": 14400, "statuses_count": 4981, "description": "Manchester United", "friends_count": 1179, "profile_link_color": "038543", "profile_image_url": "http://pbs.twimg.com/profile_images/450286164642000896/ubXyxex5_normal.jpeg", "notifications": false, "profile_background_image_url_https": "https://pbs.twimg.com/profile_background_images/378800000178895910/z1yp9Tvs.jpeg", "profile_background_color": "ACDED6", "profile_banner_url": "https://pbs.twimg.com/profile_banners/1420206979/1389373020", "profile_background_image_url": "http://pbs.twimg.com/profile_background_images/378800000178895910/z1yp9Tvs.jpeg", "name": "\u2728", "is_translation_enabled": false, "profile_background_tile": false, "favourites_count": 365, "screen_name": "n_kurtley52", "url": null, "created_at": "Sat May 11 09:14:19 +0000 2013", "contributors_enabled": false, "time_zone": "Abu Dhabi", "profile_sidebar_border_color": "FFFFFF", "default_profile": false, "following": false, "listed_count": 2}, "geo": null, "in_reply_to_user_id_str": null, "lang": "fr", "created_at": "Sun Apr 20 18:18:35 +0000 2014", "in_reply_to_status_id_str": null, "place": null}, "user": {"follow_request_sent": false, "profile_use_background_image": true, "id": 159516469, "verified": false, "profile_text_color": "333333", "profile_image_url_https": "https://pbs.twimg.com/profile_images/451001388894793729/gM1KgpTP_normal.jpeg", "profile_sidebar_fill_color": "DDEEF6", "is_translator": false, "geo_enabled": true, "entities": {"description": {"urls": []}}, "followers_count": 320, "protected": false, "location": "Old Trafford", "default_profile_image": false, "id_str": "159516469", "lang": "en", "utc_offset": -14400, "statuses_count": 7710, "description": "18 | \u26bdMy life revolves around football. It's not a matter of life or death, it's much greater than that.\u26bd \u2764#VivaRonaldo\u2764 #MUFC \u270a\u2764", "friends_count": 434, "profile_link_color": "0084B4", "profile_image_url": "http://pbs.twimg.com/profile_images/451001388894793729/gM1KgpTP_normal.jpeg", "notifications": false, "profile_background_image_url_https": "https://abs.twimg.com/images/themes/theme1/bg.png", "profile_background_color": "C0DEED", "profile_banner_url": "https://pbs.twimg.com/profile_banners/159516469/1375267046", "profile_background_image_url": "http://abs.twimg.com/images/themes/theme1/bg.png", "name": "Marco Reus", "is_translation_enabled": false, "profile_background_tile": false, "favourites_count": 837, "screen_name": "Farhad_17", "url": null, "created_at": "Fri Jun 25 16:07:01 +0000 2010", "contributors_enabled": false, "time_zone": "Eastern Time (US & Canada)", "profile_sidebar_border_color": "C0DEED", "default_profile": true, "following": false, "listed_count": 2}, "geo": null, "in_reply_to_user_id_str": null, "lang": "fr", "created_at": "Sun Apr 20 18:21:40 +0000 2014", "in_reply_to_status_id_str": null, "place": null}