{"contributors": null, "truncated": false, "text": "RT @sassylibrarian1: @brennan_elliott And that is why I follow people like you. B/c they don't forget where they came from &amp; they are kind \u2026", "in_reply_to_status_id": null, "id": 457380759100067840, "favorite_count": 0, "source": "<a href=\"http://twitter.com/download/iphone\" rel=\"nofollow\">Twitter for iPhone</a>", "retweeted": false, "coordinates": null, "entities": {"symbols": [], "user_mentions": [{"indices": [3, 19], "screen_name": "sassylibrarian1", "id": 1707815582, "name": "Meg ", "id_str": "1707815582"}, {"indices": [21, 37], "screen_name": "brennan_elliott", "id": 1651606801, "name": "Brennan Elliott", "id_str": "1651606801"}], "hashtags": [], "urls": []}, "in_reply_to_screen_name": null, "id_str": "457380759100067840", "retweet_count": 1, "in_reply_to_user_id": null, "favorited": false, "retweeted_status": {"contributors": null, "truncated": false, "text": "@brennan_elliott And that is why I follow people like you. B/c they don't forget where they came from &amp; they are kind to weirdos like me. :)", "in_reply_to_status_id": 457354062938128384, "id": 457354315384909824, "favorite_count": 3, "source": "web", "retweeted": false, "coordinates": null, "entities": {"symbols": [], "user_mentions": [{"indices": [0, 16], "screen_name": "brennan_elliott", "id": 1651606801, "name": "Brennan Elliott", "id_str": "1651606801"}], "hashtags": [], "urls": []}, "in_reply_to_screen_name": "brennan_elliott", "id_str": "457354315384909824", "retweet_count": 1, "in_reply_to_user_id": 1651606801, "favorited": false, "user": {"follow_request_sent": false, "profile_use_background_image": true, "id": 1707815582, "verified": false, "profile_text_color": "EBB8B4", "profile_image_url_https": "https://pbs.twimg.com/profile_images/457252012405428224/p83NUnkU_normal.jpeg", "profile_sidebar_fill_color": "F5AD87", "is_translator": false, "geo_enabled": false, "entities": {"description": {"urls": []}}, "followers_count": 289, "protected": false, "location": "thelandofinterestingpeople", "default_profile_image": false, "id_str": "1707815582", "lang": "en", "utc_offset": -18000, "statuses_count": 3048, "description": "I'm passionate about the things I love - good causes, good tv, good books, good  music & good people. That's just the beginning.", "friends_count": 320, "profile_link_color": "CC0A0A", "profile_image_url": "http://pbs.twimg.com/profile_images/457252012405428224/p83NUnkU_normal.jpeg", "notifications": false, "profile_background_image_url_https": "https://abs.twimg.com/images/themes/theme8/bg.gif", "profile_background_color": "F6EBCF", "profile_banner_url": "https://pbs.twimg.com/profile_banners/1707815582/1397250632", "profile_background_image_url": "http://abs.twimg.com/images/themes/theme8/bg.gif", "name": "Meg ", "is_translation_enabled": false, "profile_background_tile": false, "favourites_count": 772, "screen_name": "sassylibrarian1", "url": null, "created_at": "Wed Aug 28 17:17:02 +0000 2013", "contributors_enabled": false, "time_zone": "Central Time (US & Canada)", "profile_sidebar_border_color": "FFFFFF", "default_profile": false, "following": false, "listed_count": 2}, "geo": null, "in_reply_to_user_id_str": "1651606801", "lang": "en", "created_at": "Sat Apr 19 03:05:40 +0000 2014", "in_reply_to_status_id_str": "457354062938128384", "place": null}, "user": {"follow_request_sent": false, "profile_use_background_image": true, "id": 1651606801, "verified": true, "profile_text_color": "333333", "profile_image_url_https": "https://pbs.twimg.com/profile_images/378800000454450211/a3f638b99dd3a68f31ca1cb2e88c8574_normal.jpeg", "profile_sidebar_fill_color": "DDEEF6", "is_translator": false, "geo_enabled": false, "entities": {"url": {"urls": [{"url": "http://t.co/q3leqvF0bh", "indices": [0, 22], "expanded_url": "http://brennan-elliott.com", "display_url": "brennan-elliott.com"}]}, "description": {"urls": []}}, "followers_count": 579, "protected": false, "location": "Los Angeles", "default_profile_image": false, "id_str": "1651606801", "lang": "en", "utc_offset": null, "statuses_count": 1379, "description": "Husband, Father, Professional Experiencer...", "friends_count": 83, "profile_link_color": "0084B4", "profile_image_url": "http://pbs.twimg.com/profile_images/378800000454450211/a3f638b99dd3a68f31ca1cb2e88c8574_normal.jpeg", "notifications": false, "profile_background_image_url_https": "https://abs.twimg.com/images/themes/theme1/bg.png", "profile_background_color": "C0DEED", "profile_banner_url": "https://pbs.twimg.com/profile_banners/1651606801/1381804431", "profile_background_image_url": "http://abs.twimg.com/images/themes/theme1/bg.png", "name": "Brennan Elliott", "is_translation_enabled": false, "profile_background_tile": false, "favourites_count": 180, "screen_name": "brennan_elliott", "url": "http://t.co/q3leqvF0bh", "created_at": "Wed Aug 07 00:12:11 +0000 2013", "contributors_enabled": false, "time_zone": null, "profile_sidebar_border_color": "C0DEED", "default_profile": true, "following": false, "listed_count": 7}, "geo": null, "in_reply_to_user_id_str": null, "lang": "en", "created_at": "Sat Apr 19 04:50:45 +0000 2014", "in_reply_to_status_id_str": null, "place": null}